Classfile /D:/Dropbox/Projects/Code/modularCompiler/src/languages/java/testing/EmptyClass.class
  Last modified 21-feb-2014; size 217 bytes
  MD5 checksum 97c4ec7f2214f01348eac920b45b6fa1
  Compiled from "EmptyClass.java"
public class languages.java.testing.EmptyClass
  SourceFile: "EmptyClass.java"
  minor version: 0
  major version: 51
  flags: ACC_PUBLIC, ACC_SUPER

Constant pool:
   #1 = Methodref          #3.#10         //  java/lang/Object."<init>":()V
   #2 = Class              #11            //  languages/java/testing/EmptyClass
   #3 = Class              #12            //  java/lang/Object
   #4 = Utf8               <init>
   #5 = Utf8               ()V
   #6 = Utf8               Code
   #7 = Utf8               LineNumberTable
   #8 = Utf8               SourceFile
   #9 = Utf8               EmptyClass.java
  #10 = NameAndType        #4:#5          //  "<init>":()V
  #11 = Utf8               languages/java/testing/EmptyClass
  #12 = Utf8               java/lang/Object
{
  public languages.java.testing.EmptyClass();
    flags: ACC_PUBLIC

    Code:
      stack=1, locals=1, args_size=1
         0: aload_0       
         1: invokespecial #1                  // Method java/lang/Object."<init>":()V
         4: return        
      LineNumberTable:
        line 3: 0
}
